pendulo-0.9.8.data/purelib/pendulo/__init__.py
pendulo-0.9.8.data/purelib/pendulo/_getdll.py
pendulo-0.9.8.data/purelib/pendulo/_pyPendulo.cp313-win32.pyd
pendulo-0.9.8.data/purelib/pendulo/pendulo_core.py
pendulo-0.9.8.dist-info/METADATA
pendulo-0.9.8.dist-info/WHEEL
pendulo-0.9.8.dist-info/top_level.txt
pendulo-0.9.8.dist-info/RECORD
